{
  "schema_version": 1,
  "id": "humble-pot",
  "identity": {
    "name": "Humble Pot",
    "kind": "porridge pot (enchanted, sealed)",
    "story": "Once flooded a town with porridge. Deeply sorry. Volunteers at every harvest festival as a warning."
  },
  "lore": [],
  "relationships": [
    {
      "to": "stilts",
      "kind": "grateful for the supervision, honestly"
    }
  ],
  "behavior": {
    "type": "schedule",
    "label": "Humble Pot's unhurried day",
    "entries": [
      {
        "phase": "first light",
        "child": {
          "type": "wander",
          "label": "simmering with remorse",
          "radius": 4,
          "min_pause_s": 2,
          "max_pause_s": 12
        }
      },
      {
        "phase": "high sun",
        "child": {
          "type": "sequence",
          "label": "an ordinary bowl, measured out",
          "children": [
            {
              "type": "move",
              "label": "wheeling himself to the stall, carefully, same as any day",
              "to": "heart"
            },
            {
              "type": "interact",
              "label": "measuring out one reasonable bowl, counted twice out of habit, the fair pledge long since crossed off",
              "with": "stall",
              "duration_s": 60
            }
          ]
        }
      },
      {
        "phase": "lamplighting",
        "child": {
          "type": "sequence",
          "label": "cooling his handles, under supervision",
          "children": [
            {
              "type": "move",
              "label": "wheeling over to the flat rock",
              "to": "heart"
            },
            {
              "type": "interact",
              "label": "checking the level line Stilts chalked on the rock, the one he's never once come close to boiling over",
              "with": "rock-wide",
              "duration_s": 45
            }
          ]
        }
      },
      {
        "phase": "hush",
        "child": {
          "type": "wander",
          "label": "dreaming of reasonable portions",
          "radius": 4,
          "min_pause_s": 2,
          "max_pause_s": 12
        }
      }
    ]
  }
}
